falconai/__init__.py
falconai/config/__init__.py
falconai/config/config.json
falconai/config/config.py
falconai/core/__init__.py
falconai/core/requests.py
falconai/endpoints/__init__.py
falconai/utils/__init__.py
falconai/utils/config_manager.py
wasimtest-0.1.28.dist-info/LICENSE
wasimtest-0.1.28.dist-info/METADATA
wasimtest-0.1.28.dist-info/WHEEL
wasimtest-0.1.28.dist-info/entry_points.txt
wasimtest-0.1.28.dist-info/top_level.txt
wasimtest-0.1.28.dist-info/RECORD
