Metadata-Version: 2.1
Name: wasimtest
Version: 0.1.28
Summary: SDK for Falcon AI.
Home-page: https://bitbucket.org/northbay/generative_ai/
Author: Falcon
Author-email: wasim.khan@northbaysolutions.net
License: MIT
Classifier: License :: OSI Approved :: MIT License
Classifier: Programming Language :: Python :: 3
License-File: LICENSE
Requires-Dist: httpx
Provides-Extra: test
Requires-Dist: nose ; extra == 'test'
